setup.py
docs/README.md
docs/src/PLACE_YOUR_DOCS_HERE
docs/src/_config.yml
docs/src/_toc.yml
docs/src/intro.md
docs/src/logo.png
docs/src/references.bib
docs/src/_images/favicon.ico
docs/src/_static/ADD_CSS_AND_JS_FILES_HERE
docs/src/part_1/chapter_a/index.md
docs/src/part_1/chapter_a/section_1.md
docs/src/part_2/chapter_b/index.md
docs/src/part_2/chapter_b/section_1.md
docs/src/part_2/chapter_c/index.md
docs/src/part_2/chapter_c/section_1.md
docs/src/part_2/chapter_c/section_2.md
html/HTML_DOCS_WILL_BE_GENERATED_HERE
notebooks/.gitignore
notebooks/00-hello.ipynb
notebooks/Makefile
notebooks/README.md
notebooks/custom.css
notebooks/execute.sh
notebooks-extra/00-private.ipynb
notebooks-extra/README.md
pdf/PDF_WILL_BE_GENERATED_HERE
src/duckietown/__init__.py
src/duckietown/sdk/__init__.py
src/duckietown/sdk/types.py
src/duckietown/sdk/middleware/__init__.py
src/duckietown/sdk/middleware/base.py
src/duckietown/sdk/middleware/dtps/__init__.py
src/duckietown/sdk/middleware/dtps/base.py
src/duckietown/sdk/middleware/dtps/components.py
src/duckietown/sdk/robots/__init__.py
src/duckietown/sdk/robots/duckiebot/__init__.py
src/duckietown/sdk/robots/duckiebot/db21j.py
src/duckietown/sdk/robots/duckiebot/db21m.py
src/duckietown/sdk/robots/duckiebot/generic.py
src/duckietown/sdk/utils/__init__.py
src/duckietown/sdk/utils/jpeg.py
src/duckietown/sdk/utils/lane_position.py
src/duckietown_sdk.egg-info/PKG-INFO
src/duckietown_sdk.egg-info/SOURCES.txt
src/duckietown_sdk.egg-info/dependency_links.txt
src/duckietown_sdk.egg-info/entry_points.txt
src/duckietown_sdk.egg-info/requires.txt
src/duckietown_sdk.egg-info/top_level.txt