Metadata-Version: 2.1
Name: duckietown-sdk
Version: 0.1.4
Summary: UNKNOWN
Home-page: http://github.com/duckietown/duckietown-sdk
Author: Andrea F. Daniele
Author-email: afdaniele@duckietown.com
License: UNKNOWN
Platform: UNKNOWN
